rsmqctl/__init__.py
rsmqctl/rsmqctl.py
rsmqctl-1.0.0.dist-info/LICENSE.txt
rsmqctl-1.0.0.dist-info/METADATA
rsmqctl-1.0.0.dist-info/WHEEL
rsmqctl-1.0.0.dist-info/entry_points.txt
rsmqctl-1.0.0.dist-info/top_level.txt
rsmqctl-1.0.0.dist-info/RECORD
